netfend_waf_client/__init__.py
netfend_waf_client/waf_client.py
netfend_waf_client-2.0.0.dist-info/METADATA
netfend_waf_client-2.0.0.dist-info/WHEEL
netfend_waf_client-2.0.0.dist-info/top_level.txt
netfend_waf_client-2.0.0.dist-info/RECORD
