Metadata-Version: 2.4
Name: netfend-waf-client
Version: 2.0.0
Summary: WAF Client SDK for Python - Netfend
Home-page: https://github.com/Shieldhaus/netfend_waf_client
Author: Seu Nome
Author-email: support@netfend.emailsbit.com
Classifier: Programming Language :: Python :: 3
Classifier: Operating System :: OS Independent
Requires-Python: >=3.7
Requires-Dist: aiohttp
Requires-Dist: fastapi
Requires-Dist: flask
Requires-Dist: requests
Dynamic: author
Dynamic: author-email
Dynamic: classifier
Dynamic: home-page
Dynamic: requires-dist
Dynamic: requires-python
Dynamic: summary
